ontocop/__init__.py
ontocop-0.2.0.dist-info/LICENSE.md
ontocop-0.2.0.dist-info/METADATA
ontocop-0.2.0.dist-info/WHEEL
ontocop-0.2.0.dist-info/entry_points.txt
ontocop-0.2.0.dist-info/RECORD
