Metadata-Version: 2.1
Name: ontocop
Version: 0.2.0
Summary: A toolbox for checking ontologies
Home-page: https://gitlab.com/lukasmu/ontocop
License: MIT
Keywords: ontology,rdf,owl
Author: Lukas Müller
Author-email: hello@lukasmu.com
Requires-Python: >=3.8.1,<4.0.0
Classifier: Development Status :: 3 - Alpha
Classifier: License :: OSI Approved :: MIT License
Classifier: Operating System :: OS Independent
Classifier: Programming Language :: Python :: 3
Classifier: Programming Language :: Python :: 3.9
Classifier: Programming Language :: Python :: 3.10
Classifier: Programming Language :: Python :: 3.11
Requires-Dist: lxml (>=4.9.3,<5.0.0)
Requires-Dist: owlready2 (>=0.44,<0.45)
Requires-Dist: rdflib (>=7.0.0,<8.0.0)
Requires-Dist: requests (>=2.31.0,<3.0.0)
